{
	"info": {
		"_postman_id": "5f358677-f0c3-4927-acf6-9859a25493b6",
		"name": "spring-boot-rest-example",
		"schema": "https://schema.getpostman.com/json/collection/v2.1.0/collection.json"
	},
	"item": [
		{
			"name": "Crear Persona",
			"event": [
				{
					"listen": "prerequest",
					"script": {
						"exec": [
							"console.log(pm.info.iteration);\r",
							"pm.environment.set(\"id\", pm.info.iteration);"
						],
						"type": "text/javascript"
					}
				}
			],
			"request": {
				"method": "POST",
				"header": [
					{
						"key": "Content-Type",
						"value": "application/json"
					}
				],
				"body": {
					"mode": "raw",
					"raw": "{\n    \"name\":\"{{$randomFullName}}\",\n    \"rut\": \"1111111111\"\n}"
				},
				"url": {
					"raw": "https://api-personas-rrhh-personas-coordinador-dev.apps.prod-os-1.coordinador.cl/v1/gerencia/departamento/funcionalidad/create",
					"protocol": "https",
					"host": [
						"api-personas-rrhh-personas-coordinador-dev",
						"apps",
						"prod-os-1",
						"coordinador",
						"cl"
					],
					"path": [
						"v1",
						"gerencia",
						"departamento",
						"funcionalidad",
						"create"
					]
				}
			},
			"response": []
		},
		{
			"name": "Listar Personas",
			"event": [
				{
					"listen": "prerequest",
					"script": {
						"exec": [
							"console.log(pm.info.iteration);\r",
							"pm.environment.set(\"id\", pm.info.iteration);"
						],
						"type": "text/javascript"
					}
				}
			],
			"request": {
				"method": "GET",
				"header": [],
				"url": {
					"raw": "https://api-personas-rrhh-personas-coordinador-dev.apps.prod-os-1.coordinador.cl/v1/gerencia/departamento/funcionalidad/findAll",
					"protocol": "https",
					"host": [
						"api-personas-rrhh-personas-coordinador-dev",
						"apps",
						"prod-os-1",
						"coordinador",
						"cl"
					],
					"path": [
						"v1",
						"gerencia",
						"departamento",
						"funcionalidad",
						"findAll"
					]
				}
			},
			"response": []
		},
		{
			"name": "Buscar Persona por Id",
			"event": [
				{
					"listen": "prerequest",
					"script": {
						"exec": [
							"console.log(pm.info.iteration);\r",
							"pm.environment.set(\"id\", pm.info.iteration);"
						],
						"type": "text/javascript"
					}
				}
			],
			"request": {
				"method": "GET",
				"header": [],
				"url": {
					"raw": "https://api-personas-rrhh-personas-coordinador-dev.apps.prod-os-1.coordinador.cl/v1/gerencia/departamento/funcionalidad/findById/{{id}}",
					"protocol": "https",
					"host": [
						"api-personas-rrhh-personas-coordinador-dev",
						"apps",
						"prod-os-1",
						"coordinador",
						"cl"
					],
					"path": [
						"v1",
						"gerencia",
						"departamento",
						"funcionalidad",
						"findById",
						"{{id}}"
					]
				}
			},
			"response": []
		},
		{
			"name": "Buscar Persona por atributo",
			"event": [
				{
					"listen": "prerequest",
					"script": {
						"exec": [
							"console.log(pm.info.iteration);\r",
							"pm.environment.set(\"id\", pm.info.iteration);"
						],
						"type": "text/javascript"
					}
				}
			],
			"request": {
				"method": "GET",
				"header": [],
				"url": {
					"raw": "https://api-personas-rrhh-personas-coordinador-dev.apps.prod-os-1.coordinador.cl/v1/gerencia/departamento/funcionalidad/findByRut/{{id}}",
					"protocol": "https",
					"host": [
						"api-personas-rrhh-personas-coordinador-dev",
						"apps",
						"prod-os-1",
						"coordinador",
						"cl"
					],
					"path": [
						"v1",
						"gerencia",
						"departamento",
						"funcionalidad",
						"findByRut",
						"{{id}}"
					]
				}
			},
			"response": []
		},
		{
			"name": "Eliminar persona por Id",
			"event": [
				{
					"listen": "prerequest",
					"script": {
						"exec": [
							"console.log(pm.info.iteration);\r",
							"pm.environment.set(\"id\", pm.info.iteration);"
						],
						"type": "text/javascript"
					}
				}
			],
			"request": {
				"method": "DELETE",
				"header": [],
				"url": {
					"raw": "https://api-personas-rrhh-personas-coordinador-dev.apps.prod-os-1.coordinador.cl/v1/gerencia/departamento/funcionalidad/delete/{{id}}",
					"protocol": "https",
					"host": [
						"api-personas-rrhh-personas-coordinador-dev",
						"apps",
						"prod-os-1",
						"coordinador",
						"cl"
					],
					"path": [
						"v1",
						"gerencia",
						"departamento",
						"funcionalidad",
						"delete",
						"{{id}}"
					]
				}
			},
			"response": []
		},
		{
			"name": "Crear Crumb Jenkins",
			"request": {
				"auth": {
					"type": "basic",
					"basic": [
						{
							"key": "username",
							"value": "{username}",
							"type": "string"
						},
						{
							"key": "password",
							"value": "{password}",
							"type": "string"
						}
					]
				},
				"method": "GET",
				"header": [],
				"url": {
					"raw": "http://jenkins-url:8080/crumbIssuer/api/json",
					"protocol": "http",
					"host": [
						"jenkins-url"
					],
					"port": "8080",
					"path": [
						"crumbIssuer",
						"api",
						"json"
					]
				}
			},
			"response": []
		},
		{
			"name": "Obtener config.xml",
			"request": {
				"auth": {
					"type": "basic",
					"basic": [
						{
							"key": "username",
							"value": "jenkins-user",
							"type": "string"
						},
						{
							"key": "password",
							"value": "$jenkins-pass",
							"type": "string"
						}
					]
				},
				"method": "GET",
				"header": [],
				"url": {
					"raw": "http://jenkins-url:8080/job/$Folder/job/$nombre-pipeline/config.xml",
					"protocol": "http",
					"host": [
						"jenkins-url"
					],
					"port": "8080",
					"path": [
						"job",
						"$Folder",
						"job",
						"$nombre-pipeline",
						"config.xml"
					]
				}
			},
			"response": []
		},
		{
			"name": "Crear pipeline con config.xml",
			"request": {
				"auth": {
					"type": "basic",
					"basic": [
						{
							"key": "username",
							"value": "user_jenkins",
							"type": "string"
						},
						{
							"key": "password",
							"value": "$token_api_jenkins",
							"type": "string"
						}
					]
				},
				"method": "POST",
				"header": [
					{
						"key": "Content-Type",
						"value": "text/xml"
					}
				],
				"body": {
					"mode": "raw",
					"raw": "@config.xml"
				},
				"url": {
					"raw": "http://jenkins-url:8080/job/${Folder}/createItem?name=api-personas-rrhh-personas",
					"protocol": "http",
					"host": [
						"jenkins-url"
					],
					"port": "8080",
					"path": [
						"job",
						"${Folder}",
						"createItem"
					],
					"query": [
						{
							"key": "name",
							"value": "api-personas-rrhh-personas"
						}
					]
				}
			},
			"response": []
		}
	]
}